tinymoss/__init__.py
tinymoss/connections/__init__.py
tinymoss/connections/amqp_connection.py
tinymoss/connections/mqtt_connection.py
tinymoss/nodes/__init__.py
tinymoss-0.0.17.dist-info/METADATA
tinymoss-0.0.17.dist-info/WHEEL
tinymoss-0.0.17.dist-info/RECORD
